{
  "allowHttpBackend": false,
  "backendCommand": "",
  "backendFolderName": "",
  "certificateExceptions": [],
  "extensionViews": [
    {
      "channelId": "31692174",
      "configurationAnchor": "video_overlay",
      "displayChannelName": "bluerikoroo",
      "features": {
        "isBitsEnabled": false,
        "isChatEnabled": false,
        "isSubscriptionStatusAvailable": false
      },
      "frameSize": {
        "width": 852,
        "height": 480
      },
      "id": "1",
      "isPopout": false,
      "label": "",
      "linked": false,
      "linkedUserId": "",
      "orientation": "Portrait",
      "type": "video_overlay",
      "viewerType": "Broadcaster"
    }
  ],
  "manifest": {
    "anchor": "video_overlay",
    "assetUrls": [],
    "authorName": "Aaron",
    "bitsEnabled": false,
    "canInstall": true,
    "configUrl": "https://localhost:8080/config.html",
    "configurationLocation": "hosted",
    "description": "This is my first extention designed specifically for my own stream. I intend to use this extention to create dynamic twitch interactions with my stream.",
    "eulaTosUrl": "",
    "hasChatSupport": false,
    "iconUrl": "",
    "iconUrls": {},
    "id": "qillvtd91t2sywoxafyag186blg8jy",
    "installationCount": -42,
    "liveConfigUrl": "",
    "name": "NoraaOverlayClickDetector",
    "panelHeight": 0,
    "privacyPolicyUrl": "",
    "requestIdentityLink": false,
    "requiredBroadcasterAbilities": [],
    "screenshotUrls": [],
    "sku": "",
    "state": "Testing",
    "subscriptionsSupportLevel": "none",
    "summary": "The design of this extention is to track where on the screen the viewere clicked and transmit that to an external server.",
    "supportEmail": "Aaron1997ps@gmail.com",
    "vendorCode": "",
    "version": "0.0.1",
    "viewerSummary": "",
    "viewerUrl": "",
    "viewerUrls": {
      "videoOverlay": "https://localhost:8080/video_overlay.html"
    },
    "views": {
      "videoOverlay": {
        "viewerUrl": "https://localhost:8080/video_overlay.html",
        "canLinkExternalContent": false
      },
      "config": {
        "viewerUrl": "https://localhost:8080/config.html",
        "canLinkExternalContent": false
      }
    },
    "whitelistedConfigUrls": [],
    "whitelistedPanelUrls": []
  },
  "frontendCommand": "",
  "frontendFolderName": "C:\\Users\\Aaron\\Desktop\\NoraaWebsocketShanangans\\",
  "name": "NoraaOverlayClickDetector",
  "usingRandomFrontendHostingPort": true,
  "version": 3
}